qwen_api/__init__.py
qwen_api/client.py
qwen_api/logger.py
qwen_api/core/__init__.py
qwen_api/core/auth_manager.py
qwen_api/core/config.py
qwen_api/core/exceptions.py
qwen_api/core/types/chat.py
qwen_api/core/types/chat_model.py
qwen_api/core/types/endpoint_api.py
qwen_api/core/types/pydantic.py
qwen_api/core/types/schema.py
qwen_api/core/types/upload_file.py
qwen_api/core/types/response/function_tool.py
qwen_api/core/types/response/tool_param.py
qwen_api/resources/completions.py
qwen_api/resources/tool_handle.py
qwen_api/utils/image_llamaindex.py
qwen_api/utils/promp_system.py
qwen_api/utils/tool_helper.py
qwen_api/utils/tool_prompt.py
qwen_api-1.4.16.dist-info/METADATA
qwen_api-1.4.16.dist-info/WHEEL
qwen_api-1.4.16.dist-info/top_level.txt
qwen_api-1.4.16.dist-info/RECORD
