Metadata-Version: 2.4
Name: qwen-api
Version: 1.4.16
Summary: Unofficial Qwen API Client
Author-email: Ahmad Rosyihuddin <rosyihuddin.dev@gmail.com>
License: MIT
Project-URL: Homepage, https://github.com/arosyihuddin/qwen-api
Project-URL: Documentation, https://github.com/arosyihuddin/qwen-api
Project-URL: Repository, https://github.com/arosyihuddin/qwen-api
Project-URL: Issues, https://github.com/arosyihuddin/qwen-api/issues
Keywords: qwen,ai,llm,qwen-api
Classifier: Development Status :: 5 - Production/Stable
Classifier: Intended Audience :: Developers
Classifier: Topic :: Software Development :: Build Tools
Classifier: Programming Language :: Python :: 3
Classifier: Programming Language :: Python :: 3.11
Classifier: Programming Language :: Python :: 3.12
Classifier: Programming Language :: Python :: 3.13
Classifier: License :: OSI Approved :: MIT License
Classifier: Operating System :: OS Independent
Requires-Python: >=3.11
Requires-Dist: requests>=2.32.3
Requires-Dist: python-dotenv>=1.1.0
Requires-Dist: sseclient-py>=1.8.0
Requires-Dist: pydantic>=2.11.4
Requires-Dist: aiohttp>=3.11.18
Requires-Dist: colorama>=0.4.6
Requires-Dist: oss2<3.0.0,>=2.19.1
Requires-Dist: filetype<2.0.0,>=1.2.0
Provides-Extra: dev
Requires-Dist: pytest; extra == "dev"
Requires-Dist: black; extra == "dev"
Requires-Dist: mypy; extra == "dev"
